LICENSE
MANIFEST.in
README.rst
setup.py
django_monsieur.egg-info/PKG-INFO
django_monsieur.egg-info/SOURCES.txt
django_monsieur.egg-info/dependency_links.txt
django_monsieur.egg-info/top_level.txt
monsieur/__init__.py
monsieur/models.py
monsieur/tests.py
monsieur/urls.py
monsieur/views.py