Metadata-Version: 1.0
Name: django-monsieur
Version: 0.0.2
Summary: .
Home-page: https://github.com/emef/django-monsieur
Author: Matt Forbes
Author-email: matt.r.forbes@gmail.com
License: BSD
Platform: UNKNOWN
Classifier: Development Status :: 4 - Beta
Classifier: Environment :: Web Environment
Classifier: Framework :: Django
Classifier: Intended Audience :: Developers
Classifier: License :: OSI Approved :: BSD License
Classifier: Operating System :: OS Independent
Classifier: Programming Language :: Python
Classifier: Topic :: Software Development :: Libraries :: Python Modules
